lgws/__init__.py
lgws/__main__.py
lgws/bridge.py
lgws/cli.py
lgws/lgws.py
lgws/utils.py
lgws-0.0.1.dist-info/entry_points.txt
lgws-0.0.1.dist-info/LICENSE
lgws-0.0.1.dist-info/WHEEL
lgws-0.0.1.dist-info/METADATA
lgws-0.0.1.dist-info/RECORD
